fun_with_ast/__init__.py
fun_with_ast/common_utils/__init__.py
fun_with_ast/common_utils/constant_visitor.py
fun_with_ast/common_utils/node_tree_util.py
fun_with_ast/common_utils/parenthese_stack.py
fun_with_ast/common_utils/stack.py
fun_with_ast/common_utils/utils_source_match.py
fun_with_ast/get_source.py
fun_with_ast/lazy_dict.py
fun_with_ast/manipulate_node/__init__.py
fun_with_ast/manipulate_node/body_manipulator.py
fun_with_ast/manipulate_node/call_args_node.py
fun_with_ast/manipulate_node/create_node.py
fun_with_ast/manipulate_node/get_node_from_input.py
fun_with_ast/manipulate_node/if_manipulator.py
fun_with_ast/manipulate_node/nodes_for_jstr.py
fun_with_ast/manipulate_node/syntax_free_line_node.py
fun_with_ast/placeholders/__init__.py
fun_with_ast/placeholders/args.py
fun_with_ast/placeholders/base_match.py
fun_with_ast/placeholders/base_placeholder.py
fun_with_ast/placeholders/composite.py
fun_with_ast/placeholders/docstring.py
fun_with_ast/placeholders/kwonlyargs.py
fun_with_ast/placeholders/list_placeholder.py
fun_with_ast/placeholders/node.py
fun_with_ast/placeholders/string_parser.py
fun_with_ast/placeholders/string_part.py
fun_with_ast/placeholders/text.py
fun_with_ast/placeholders/whitespace.py
fun_with_ast/setup.py
fun_with_ast/source_match.py
fun_with_ast/source_matchers/__init__.py
fun_with_ast/source_matchers/base_matcher.py
fun_with_ast/source_matchers/body.py
fun_with_ast/source_matchers/boolop.py
fun_with_ast/source_matchers/constant_jstr_matcher.py
fun_with_ast/source_matchers/constant_source_match.py
fun_with_ast/source_matchers/defualt_matcher.py
fun_with_ast/source_matchers/exceptions.py
fun_with_ast/source_matchers/if_source_match.py
fun_with_ast/source_matchers/joined_str_config.py
fun_with_ast/source_matchers/joined_str_new.py
fun_with_ast/source_matchers/lambda_matcher.py
fun_with_ast/source_matchers/matcher_resolver.py
fun_with_ast/source_matchers/reset_match.py
fun_with_ast/source_matchers/str.py
fun_with_ast-0.2.118.dist-info/LICENSE
fun_with_ast-0.2.118.dist-info/METADATA
fun_with_ast-0.2.118.dist-info/WHEEL
fun_with_ast-0.2.118.dist-info/RECORD
