Metadata-Version: 2.1
Name: fun-with-ast
Version: 0.2.118
Summary: 
Author: Shai Rubin
Author-email: shai@ownbackup.com
Requires-Python: >=3.10,<4.0
Classifier: Programming Language :: Python :: 3
Classifier: Programming Language :: Python :: 3.10
Classifier: Programming Language :: Python :: 3.11
Classifier: Programming Language :: Python :: 3.12
Classifier: Programming Language :: Python :: 3.13
